tableau_helpers/__init__.py
tableau_helpers/hyper.py
tableau_helpers/server.py
tableau_helpers/utils.py
tableau_helpers/cli/__init__.py
tableau_helpers/cli/csv_to_hyper.py
tableau_helpers/cli/logs.py
tableau_helpers/cli/upload_csv.py
tableau_helpers/cli/upload_hyper.py
tableau_helpers-2.0.5.dist-info/LICENSE
tableau_helpers-2.0.5.dist-info/METADATA
tableau_helpers-2.0.5.dist-info/WHEEL
tableau_helpers-2.0.5.dist-info/entry_points.txt
tableau_helpers-2.0.5.dist-info/top_level.txt
tableau_helpers-2.0.5.dist-info/RECORD
