Metadata-Version: 2.1
Name: tableau-helpers
Version: 2.0.5
Summary: A collection of helpers to reduce boilerplate with Tableau APIs.
License: MIT License
Requires-Python: >=3.4
License-File: LICENSE
Requires-Dist: tableauhyperapi ==0.0.17002
Requires-Dist: tableauserverclient ==0.25.0
Requires-Dist: python-dotenv
Requires-Dist: pip-system-certs >=4.0 ; platform_system == "Windows"
Provides-Extra: dev
Requires-Dist: pre-commit ; extra == 'dev'
Requires-Dist: black ; extra == 'dev'
Requires-Dist: ruff ; extra == 'dev'
Requires-Dist: pylint ; extra == 'dev'
Requires-Dist: pyright ; extra == 'dev'
Provides-Extra: test
Requires-Dist: pytest ; extra == 'test'
